LICENSE
README.md
setup.cfg
setup.py
compile_env/__init__.py
compile_env.egg-info/PKG-INFO
compile_env.egg-info/SOURCES.txt
compile_env.egg-info/dependency_links.txt
compile_env.egg-info/entry_points.txt
compile_env.egg-info/not-zip-safe
compile_env.egg-info/requires.txt
compile_env.egg-info/top_level.txt